sentiframe/__init__.py
sentiframe/analyzer.py
sentiframe/base_scraper.py
sentiframe/utils.py
sentiframe/youtube_api.py
sentiframe/youtube_scraper.py
sentiframe-0.1.0.dist-info/METADATA
sentiframe-0.1.0.dist-info/WHEEL
sentiframe-0.1.0.dist-info/entry_points.txt
sentiframe-0.1.0.dist-info/top_level.txt
sentiframe-0.1.0.dist-info/RECORD
