Metadata-Version: 2.2
Name: sentiframe
Version: 0.1.0
Summary: A flexible framework for scraping and analyzing YouTube comments
Home-page: https://github.com/ayushrawat220804/sentiframe
Author: Ayush Rawat
Author-email: ayushrawat220804@gmail.com
Project-URL: Bug Reports, https://github.com/ayushrawat220804/sentiframe/issues
Project-URL: Source, https://github.com/ayushrawat220804/sentiframe
Project-URL: Documentation, https://github.com/ayushrawat220804/sentiframe#readme
Keywords: youtube,comments,analysis,sentiment,api
Classifier: Development Status :: 3 - Alpha
Classifier: Intended Audience :: Developers
Classifier: License :: OSI Approved :: MIT License
Classifier: Operating System :: OS Independent
Classifier: Programming Language :: Python :: 3
Classifier: Programming Language :: Python :: 3.7
Classifier: Programming Language :: Python :: 3.8
Classifier: Programming Language :: Python :: 3.9
Classifier: Programming Language :: Python :: 3.10
Classifier: Topic :: Internet :: WWW/HTTP
Classifier: Topic :: Software Development :: Libraries :: Python Modules
Requires-Python: >=3.7
Requires-Dist: google-api-python-client>=2.108.0
Requires-Dist: python-dotenv>=1.0.0
Requires-Dist: pandas>=1.3.0
Provides-Extra: web
Requires-Dist: streamlit>=1.29.0; extra == "web"
Provides-Extra: dev
Requires-Dist: pytest>=7.0.0; extra == "dev"
Requires-Dist: black>=22.0.0; extra == "dev"
Requires-Dist: isort>=5.0.0; extra == "dev"
Requires-Dist: flake8>=4.0.0; extra == "dev"
Dynamic: author
Dynamic: author-email
Dynamic: classifier
Dynamic: description
Dynamic: description-content-type
Dynamic: home-page
Dynamic: keywords
Dynamic: project-url
Dynamic: provides-extra
Dynamic: requires-dist
Dynamic: requires-python
Dynamic: summary
